Workbook

Sheet 使用说明
B1: 杜邦分析项目 · 财务数据录入模板（苏泊尔 002032 + 三家对标）
B3: 1. 数据来源：各公司年报 PDF 中「财务报告」一节的【合并资产负债表】与【合并利润表】。巨潮资讯网页汇总表仅作交叉核对，不作为录入来源（缺归母权益、费用明细等关键科目）。
B4: 2. 单位：元（与年报原文一致，照抄即可，不做任何换算）。Power BI 中再统一格式化为亿元显示。
B5: 3. 颜色约定：黄色底 = 需要你填写的单元格；蓝色字 = 已预填的数值（示例行）；黑色字 = 公式，请勿改动。
B6: 4. 示例行说明：「利润表」与「资产负债表」中苏泊尔 2025 年的部分单元格已按巨潮页面预填（万元×10000 换算为元），格式仅供参考，录入时请以年报 PDF 原文逐项核对并补齐该行黄色单元格。
B7: 5. 录入范围：苏泊尔——资产负债表 2020–2025 共 6 年（2020 年只需资产负债表，用于计算 2021 年平均数），利润表 2021–2025 共 5 年；三家对标（九阳股份 002242 / 小熊电器 002959 / 新宝股份 002705）——资产负债表 2022–2025，利润表 2023–2025。
B8: 6. 每录完一行，看该行最后的「勾稽校验」列：差额应为 0（允许 ±1 元的四舍五入差）。不为 0 说明抄错了数，当场改。
B9: 7. 「杜邦速算」表全部为公式，自动汇总。录完苏泊尔后先看它的 ROE 曲线是否与年报披露的加权 ROE 大致吻合（口径为期初期末平均，略有差异属正常）。
B10: 8. 归母口径提醒：ROE 分母必须用【归属于母公司所有者权益】，不是所有者权益合计——这两个科目在年报资产负债表中是分开列示的两行，别抄混。

Sheet 利润表
A1: 公司代码 | B1: 公司简称 | C1: 年份 | D1: 营业总收入 | E1: 营业收入 | F1: 营业成本 | G1: 销售费用 | H1: 管理费用 | I1: 研发费用 | J1: 财务费用 | K1: 营业利润 | L1: 利润总额 | M1: 所得税费用 | N1: 净利润 | O1: 归属于母公司股东的净利润 | P1: 少数股东损益 | Q1: 勾稽校验(净利润-归母-少数) | R1: 数据来源备注
A2: 002032 | B2: 苏泊尔 | C2: 2021 | D2: =21585331407.47 -> 2.1585331e+10 | E2: =21585331407.47 -> 2.1585331e+10 | F2: =16621613160.8 -> 1.6621613e+10 | G2: =1909953095.54 -> 1.9099531e+09 | H2: =400779608.67 -> 4.0077961e+08 | I2: =450110510.51 -> 4.5011051e+08 | J2: =-6482301.16 -> -6482301.2 | K2: =2385111931.58 -> 2.3851119e+09 | L2: =2385781578.96 -> 2.3857816e+09 | M2: =444410051.07 -> 4.4441005e+08 | N2: =1941371527.89 -> 1.9413715e+09 | O2: =1943943608.94 -> 1.9439436e+09 | P2: =-2572081.05 -> -2572081 | Q2: =IF(COUNT(N2:P2)<3,"",N2-O2-P2) -> 4.7497451e-08 | R2: 2021年报（官网获取）
A3: 002032 | B3: 苏泊尔 | C3: 2022 | D3: =20170527516.66 -> 2.0170528e+10 | E3: =20170527516.66 -> 2.0170528e+10 | F3: =14969328840.57 -> 1.4969329e+10 | G3: =2156297058.63 -> 2.1562971e+09 | H3: =374060640.28 -> 3.7406064e+08 | I3: =416259356.99 -> 4.1625936e+08 | J3: =-97423287.91 -> -97423288 | K3: =2535238829.73 -> 2.5352388e+09 | L3: =2545209603.98 -> 2.5452096e+09 | M3: =479033164.36 -> 4.7903316e+08 | N3: =2066176439.62 -> 2.0661764e+09 | O3: =2067659526.97 -> 2.0676595e+09 | P3: =-1483087.35 -> -1483087.4 | Q3: =IF(COUNT(N3:P3)<3,"",N3-O3-P3) -> -1.4295802e-07 | R3: 2022年报（官网获取）
A4: 002032 | B4: 苏泊尔 | C4: 2023 | D4: =21303948642.66 -> 2.1303949e+10 | E4: =21303948642.66 -> 2.1303949e+10 | F4: =15918445100.1 -> 1.5918445e+10 | G4: =2079531174.95 -> 2.0795312e+09 | H4: =393597966.82 -> 3.9359797e+08 | I4: =431288536.29 -> 4.3128854e+08 | J4: =-67629941.36 -> -67629941 | K4: =2681323324.18 -> 2.6813233e+09 | L4: =2684718454.7 -> 2.6847185e+09 | M4: =505298017.49 -> 5.0529802e+08 | N4: =2179420437.21 -> 2.1794204e+09 | O4: =2179798147.27 -> 2.1797981e+09 | P4: =-377710.06 -> -377710.06 | Q4: =IF(COUNT(N4:P4)<3,"",N4-O4-P4) -> 5.7218131e-08 | R4: 2023年报（官网获取）
A5: 002032 | B5: 苏泊尔 | C5: 2024 | D5: =22427337986.38 -> 2.2427338e+10 | E5: =22427337986.38 -> 2.2427338e+10 | F5: =16898273538.62 -> 1.6898274e+10 | G5: =2181958549.81 -> 2.1819585e+09 | H5: =396033243.5 -> 3.9603324e+08 | I5: =469662999.96 -> 4.69663e+08 | J5: =-72445787.56 -> -72445788 | K5: =2732270616.35 -> 2.7322706e+09 | L5: =2732357095.86 -> 2.7323571e+09 | M5: =487113115.06 -> 4.8711312e+08 | N5: =2245243980.8 -> 2.245244e+09 | O5: =2244444529.35 -> 2.2444445e+09 | P5: =799451.45 -> 799451.45 | Q5: =IF(COUNT(N5:P5)<3,"",N5-O5-P5) -> 2.8614886e-07 | R5: 2024年报（官网获取）
A6: 002032 | B6: 苏泊尔 | C6: 2025 | D6: =22771753460.04 -> 2.2771753e+10 | E6: =22771753460.04 -> 2.2771753e+10 | F6: =17109148068.46 -> 1.7109148e+10 | G6: =2409003037.6 -> 2.409003e+09 | H6: =399940362.79 -> 3.9994036e+08 | I6: =475923455.1 -> 4.7592346e+08 | J6: =-16240989.26 -> -16240989 | K6: =2587783351.81 -> 2.5877834e+09 | L6: =2587527158.14 -> 2.5875272e+09 | M6: =493214128.84 -> 4.9321413e+08 | N6: =2094313029.3 -> 2.094313e+09 | O6: =2096720231.52 -> 2.0967202e+09 | P6: =-2407202.22 -> -2407202.2 | Q6: =IF(COUNT(N6:P6)<3,"",N6-O6-P6) -> -2.8405339e-08 | R6: 2025年报（官网获取）
A7: 002242 | B7: 九阳股份 | C7: 2023 | D7: =9612788761.39 -> 9.6127888e+09 | E7: =9612788761.39 -> 9.6127888e+09 | F7: =7224778348.79 -> 7.2247783e+09 | G7: =1327924995.51 -> 1.327925e+09 | H7: =381026947.16 -> 3.8102695e+08 | I7: =388911162.61 -> 3.8891116e+08 | J7: =-62244556.28 -> -62244556 | K7: =434045919.75 -> 4.3404592e+08 | L7: =430912074.11 -> 4.3091207e+08 | M7: =40363232.33 -> 40363232 | N7: =390548841.78 -> 3.9054884e+08 | O7: =389046168.9 -> 3.8904617e+08 | P7: =1502672.88 -> 1502672.9 | Q7: =IF(COUNT(N7:P7)<3,"",N7-O7-P7) -> -4.6566129e-09 | R7: 2023年报（东方财富网）
A8: 002242 | B8: 九阳股份 | C8: 2024 | D8: =8849314724.78 -> 8.8493147e+09 | E8: =8849314724.78 -> 8.8493147e+09 | F8: =6592327468.13 -> 6.5923275e+09 | G8: =1506245716.2 -> 1.5062457e+09 | H8: =384529321.6 -> 3.8452932e+08 | I8: =360966798.42 -> 3.609668e+08 | J8: =-107544191.35 -> -1.0754419e+08 | K8: =52402698.29 -> 52402698 | L8: =49073246.84 -> 49073247 | M8: =-57356200.47 -> -57356200 | N8: =106429447.31 -> 1.0642945e+08 | O8: =122351668.35 -> 1.2235167e+08 | P8: =-15922221.04 -> -15922221 | Q8: =IF(COUNT(N8:P8)<3,"",N8-O8-P8) -> 7.4505806e-09 | R8: 2024年报（东方财富网）
A9: 002242 | B9: 九阳股份 | C9: 2025 | D9: =8209763125.36 -> 8.2097631e+09 | E9: =8209763125.36 -> 8.2097631e+09 | F9: =6012016903.28 -> 6.0120169e+09 | G9: =1391577254.71 -> 1.3915773e+09 | H9: =381130615.84 -> 3.8113062e+08 | I9: =302971036.92 -> 3.0297104e+08 | J9: =-76697092.63 -> -76697093 | K9: =98609046.18 -> 98609046 | L9: =97539086.62 -> 97539087 | M9: =-19595955.73 -> -19595956 | N9: =117135042.35 -> 1.1713504e+08 | O9: =117645794.97 -> 1.1764579e+08 | P9: =-510752.62 -> -510752.62 | Q9: =IF(COUNT(N9:P9)<3,"",N9-O9-P9) -> -4.7730282e-09 | R9: 2025年报（东方财富网）
A10: 002959 | B10: 小熊电器 | C10: 2023 | D10: =4711887394.9 -> 4.7118874e+09 | E10: =4711887394.9 -> 4.7118874e+09 | F10: =2986677848.9 -> 2.9866778e+09 | G10: =883995473.96 -> 8.8399547e+08 | H10: =189722846.75 -> 1.8972285e+08 | I10: =142764362.8 -> 1.4276436e+08 | J10: =5290510.48 -> 5290510.5 | K10: =492357727.01 -> 4.9235773e+08 | L10: =514684364.28 -> 5.1468436e+08 | M10: =69379329.08 -> 69379329 | N10: =445305035.2 -> 4.4530504e+08 | O10: =445273101.28 -> 4.452731e+08 | P10: =31933.92 -> 31933.92 | Q10: =IF(COUNT(N10:P10)<3,"",N10-O10-P10) -> 1.6691047e-08 | R10: 2023年报（官网获取）
A11: 002959 | B11: 小熊电器 | C11: 2024 | D11: =4758269988.61 -> 4.75827e+09 | E11: =4758269988.61 -> 4.75827e+09 | F11: =3078896917.99 -> 3.0788969e+09 | G11: =864470989.43 -> 8.6447099e+08 | H11: =235722652.01 -> 2.3572265e+08 | I11: =194849656.23 -> 1.9484966e+08 | J11: =14376656.29 -> 14376656 | K11: =350558390.75 -> 3.5055839e+08 | L11: =358067318.33 -> 3.5806732e+08 | M11: =51959423.55 -> 51959424 | N11: =306107894.78 -> 3.0610789e+08 | O11: =287787361.75 -> 2.8778736e+08 | P11: =18320533.03 -> 18320533 | Q11: =IF(COUNT(N11:P11)<3,"",N11-O11-P11) -> -2.9802322e-08 | R11: 2024年报（东方财富网）
A12: 002959 | B12: 小熊电器 | C12: 2025 | D12: =5230079556.58 -> 5.2300796e+09 | E12: =5230079556.58 -> 5.2300796e+09 | F12: =3312360032.62 -> 3.31236e+09 | G12: =916005050.75 -> 9.1600505e+08 | H12: =248967284.12 -> 2.4896728e+08 | I12: =211946389.93 -> 2.1194639e+08 | J12: =-7523370.69 -> -7523370.7 | K12: =500060333.1 -> 5.0006033e+08 | L12: =508252564.87 -> 5.0825256e+08 | M12: =88666062.02 -> 88666062 | N12: =419586502.85 -> 4.195865e+08 | O12: =392540862.97 -> 3.9254086e+08 | P12: =27045639.88 -> 27045640 | Q12: =IF(COUNT(N12:P12)<3,"",N12-O12-P12) -> -3.7252903e-09 | R12: 2025年报（东方财富网）
A13: 002705 | B13: 新宝股份 | C13: 2023 | D13: =14646752683.92 -> 1.4646753e+10 | E13: =14646752683.92 -> 1.4646753e+10 | F13: =11316459759.24 -> 1.131646e+10 | G13: =579489031.54 -> 5.7948903e+08 | H13: =860489582.59 -> 8.6048958e+08 | I13: =554690497.38 -> 5.546905e+08 | J13: =-85087066.28 -> -85087066 | K13: =1311836020.56 -> 1.311836e+09 | L13: =1307289375.42 -> 1.3072894e+09 | M13: =260673826.76 -> 2.6067383e+08 | N13: =1046615548.66 -> 1.0466155e+09 | O13: =977140300.39 -> 9.771403e+08 | P13: =69475248.27 -> 69475248 | Q13: =IF(COUNT(N13:P13)<3,"",N13-O13-P13) -> -1.4901161e-08 | R13: 2023年报（官网获取）
A14: 002705 | B14: 新宝股份 | C14: 2024 | D14: =16821049466.94 -> 1.6821049e+10 | E14: =16821049466.94 -> 1.6821049e+10 | F14: =13303310897.59 -> 1.3303311e+10 | G14: =605702880.88 -> 6.0570288e+08 | H14: =830894759.83 -> 8.3089476e+08 | I14: =662750704.72 -> 6.627507e+08 | J14: =-87760705.99 -> -87760706 | K14: =1329921124.98 -> 1.3299211e+09 | L14: =1327968831.54 -> 1.3279688e+09 | M14: =212484886.97 -> 2.1248489e+08 | N14: =1115483944.57 -> 1.1154839e+09 | O14: =1052838750.42 -> 1.0528388e+09 | P14: =62645194.15 -> 62645194 | Q14: =IF(COUNT(N14:P14)<3,"",N14-O14-P14) -> -2.2351742e-08 | R14: 2024年报（官网获取）
A15: 002705 | B15: 新宝股份 | C15: 2025 | D15: =16192053797.72 -> 1.6192054e+10 | E15: =16192053797.72 -> 1.6192054e+10 | F15: =12822922920.54 -> 1.2822923e+10 | G15: =603693235.44 -> 6.0369324e+08 | H15: =810360524.95 -> 8.1036052e+08 | I15: =549570353.82 -> 5.4957035e+08 | J15: =47454630.19 -> 47454630 | K15: =1262245791.48 -> 1.2622458e+09 | L15: =1240388450.44 -> 1.2403885e+09 | M15: =196035855.11 -> 1.9603586e+08 | N15: =1044352595.33 -> 1.0443526e+09 | O15: =999368736.37 -> 9.9936874e+08 | P15: =44983858.96 -> 44983859 | Q15: =IF(COUNT(N15:P15)<3,"",N15-O15-P15) -> 3.7252903e-08 | R15: 2025年报（官网获取）

Sheet 资产负债表
A1: 公司代码 | B1: 公司简称 | C1: 年份(年末) | D1: 货币资金 | E1: 应收账款 | F1: 存货 | G1: 流动资产合计 | H1: 非流动资产合计 | I1: 资产总计 | J1: 流动负债合计 | K1: 非流动负债合计 | L1: 负债合计 | M1: 归属于母公司所有者权益 | N1: 少数股东权益 | O1: 所有者权益合计 | P1: 勾稽校验1(资产-负债-权益) | Q1: 勾稽校验2(权益合计-归母-少数) | R1: 勾稽校验3(负债合计=流动+非流动) | S1: 勾稽校验4(资产合计=流动+非流动) | T1: 数据来源备注
A2: 002032 | B2: 苏泊尔 | C2: 2020 | D2: 1.7197859e+09 | E2: 2.2283023e+09 | F2: 2.4092987e+09 | G2: 1.0116819e+10 | H2: 2.175451e+09 | I2: 1.229227e+10 | J2: 5.0364774e+09 | K2: 19069023 | L2: 5.0555464e+09 | M2: 7.2009399e+09 | N2: 35784081 | O2: 7.236724e+09 | P2: =IF(COUNT(I2,L2,O2)<3,"",I2-L2-O2) -> -9.5367432e-07 | Q2: =IF(COUNT(M2:O2)<3,"",O2-M2-N2) -> -3.4272671e-07 | R2: =L2=K2+J2 -> TRUE | S2: =I2=G2+H2 -> TRUE | T2: 2021年报（官网获取）
A3: 002032 | B3: 苏泊尔 | C3: 2021 | D3: 2.6540524e+09 | E3: 2.716946e+09 | F3: 3.0965171e+09 | G3: 1.1158575e+10 | H3: 2.7408816e+09 | I3: 1.3899456e+10 | J3: 6.0690874e+09 | K3: 1.7206114e+08 | L3: 6.2411486e+09 | M3: 7.6226398e+09 | N3: 35668094 | O3: 7.6583078e+09 | P3: =IF(COUNT(I3,L3,O3)<3,"",I3-L3-O3) -> 0 | Q3: =IF(COUNT(M3:O3)<3,"",O3-M3-N3) -> 4.1723251e-07 | R3: =L3=K3+J3 -> TRUE | S3: =I3=G3+H3 -> TRUE | T3: 2021年报（官网获取）
A4: 002032 | B4: 苏泊尔 | C4: 2022 | D4: 3.5631409e+09 | E4: 1.9265181e+09 | F4: 2.4949229e+09 | G4: 9.5183742e+09 | H4: 3.4342817e+09 | I4: 1.2952656e+10 | J4: 5.7151042e+09 | K4: 1.6486147e+08 | L4: 5.8799657e+09 | M4: 7.0360849e+09 | N4: 36605325 | O4: 7.0726902e+09 | P4: =IF(COUNT(I4,L4,O4)<3,"",I4-L4-O4) -> 0 | Q4: =IF(COUNT(M4:O4)<3,"",O4-M4-N4) -> -2.30968e-07 | R4: =L4=K4+J4 -> TRUE | S4: =I4=G4+H4 -> TRUE | T4: 2022年报（官网获取）
A5: 002032 | B5: 苏泊尔 | C5: 2023 | D5: 3.5482774e+09 | E5: 2.8582474e+09 | F5: 2.2626834e+09 | G5: 1.0036695e+10 | H5: 3.0700091e+09 | I5: 13106703607 | J5: 6.4845778e+09 | K5: 2.4029275e+08 | L5: 6.7248705e+09 | M5: 6.345333e+09 | N5: 36500037 | O5: 6.3818331e+09 | P5: =IF(COUNT(I5,L5,O5)<3,"",I5-L5-O5) -> 0 | Q5: =IF(COUNT(M5:O5)<3,"",O5-M5-N5) -> 2.30968e-07 | R5: =L5=K5+J5 -> TRUE | S5: =I5=G5+H5 -> TRUE | T5: 2023年报（官网获取）
A6: 002032 | B6: 苏泊尔 | C6: 2024 | D6: 2.4800073e+09 | E6: 2.690049e+09 | F6: 2.5659581e+09 | G6: 1.0603927e+10 | H6: 2.6619295e+09 | I6: 1.3265857e+10 | J6: 6.5238522e+09 | K6: 2.8047715e+08 | L6: 6.8043294e+09 | M6: 6.4244143e+09 | N6: 37112980 | O6: 6.4615273e+09 | P6: =IF(COUNT(I6,L6,O6)<3,"",I6-L6-O6) -> 9.5367432e-07 | Q6: =IF(COUNT(M6:O6)<3,"",O6-M6-N6) -> 1.4901161e-07 | R6: =L6=K6+J6 -> TRUE | S6: =I6=G6+H6 -> TRUE | T6: 2024年报（官网获取）
A7: 002032 | B7: 苏泊尔 | C7: 2025 | D7: 1.9831454e+09 | E7: 2.7594205e+09 | F7: 2.4081401e+09 | G7: 1.0964909e+10 | H7: 2.4520667e+09 | I7: 1.3416976e+10 | J7: 6.8775576e+09 | K7: 2.2068527e+08 | L7: 7.0982429e+09 | M7: 6.2848597e+09 | N7: 33873154 | O7: 6.3187329e+09 | P7: =IF(COUNT(I7,L7,O7)<3,"",I7-L7-O7) -> 0 | Q7: =IF(COUNT(M7:O7)<3,"",O7-M7-N7) -> 5.7369471e-07 | R7: =L7=K7+J7 -> TRUE | S7: =I7=G7+H7 -> TRUE | T7: 2025年报（官网获取）
A8: 002242 | B8: 九阳股份 | C8: 2022 | D8: 1.5697806e+09 | E8: 6.8736052e+08 | F8: 6.8020644e+08 | G8: 4.9362895e+09 | H8: 2.1389892e+09 | I8: 7.0752787e+09 | J8: 3.6727476e+09 | K8: 75551173 | L8: 3.7482988e+09 | M8: 3.31359e+09 | N8: 13389942 | O8: 3.32698e+09 | P8: =IF(COUNT(I8,L8,O8)<3,"",I8-L8-O8) -> -4.7683716e-07 | Q8: =IF(COUNT(M8:O8)<3,"",O8-M8-N8) -> 2.2910535e-07 | R8: =L8=K8+J8 -> TRUE | S8: =I8=G8+H8 -> TRUE | T8: 2023年报（东方财富网）
A9: 002242 | B9: 九阳股份 | C9: 2023 | D9: 2.431378e+09 | E9: 1.0097692e+09 | F9: 5.5841713e+08 | G9: 5.6267699e+09 | H9: 1.9853101e+09 | I9: 7.61208e+09 | J9: 4.0665831e+09 | K9: 59249972 | L9: 4.1258331e+09 | M9: 3.4713472e+09 | N9: 14899800 | O9: 3.486247e+09 | P9: =IF(COUNT(I9,L9,O9)<3,"",I9-L9-O9) -> 0 | Q9: =IF(COUNT(M9:O9)<3,"",O9-M9-N9) -> 1.3411045e-07 | R9: =L9=K9+J9 -> TRUE | S9: =I9=G9+H9 -> TRUE | T9: 2023年报（东方财富网）
A10: 002242 | B10: 九阳股份 | C10: 2024 | D10: 2.8236834e+09 | E10: 1.0784832e+09 | F10: 6.3478816e+08 | G10: 5.7755387e+09 | H10: 1.8106471e+09 | I10: 7.5861857e+09 | J10: 4.0448319e+09 | K10: 47389022 | L10: 4.0922209e+09 | M10: 3.4858957e+09 | N10: 8069185.3 | O10: 3.4939648e+09 | P10: =IF(COUNT(I10,L10,O10)<3,"",I10-L10-O10) -> 4.7683716e-07 | Q10: =IF(COUNT(M10:O10)<3,"",O10-M10-N10) -> -2.6728958e-07 | R10: =L10=K10+J10 -> TRUE | S10: =I10=G10+H10 -> TRUE | T10: 2024年报（东方财富网）
A11: 002242 | B11: 九阳股份 | C11: 2025 | D11: 3.8023441e+09 | E11: 844530212 | F11: 5.3653128e+08 | G11: 6.182587e+09 | H11: 1.6116378e+09 | I11: 7.7942247e+09 | J11: 4.1648353e+09 | K11: 25261533 | L11: 4.1900968e+09 | M11: 3.4332411e+09 | N11: 1.7088679e+08 | O11: 3.6041279e+09 | P11: =IF(COUNT(I11,L11,O11)<3,"",I11-L11-O11) -> 4.7683716e-07 | Q11: =IF(COUNT(M11:O11)<3,"",O11-M11-N11) -> -2.9802322e-08 | R11: =L11=K11+J11 -> TRUE | S11: =I11=G11+H11 -> TRUE | T11: 2025年报（东方财富网）
A12: 002959 | B12: 小熊电器 | C12: 2022 | D12: 2.1161424e+09 | E12: 66374794 | F12: 6.508527e+08 | G12: 3.6156481e+09 | H12: 1.2596896e+09 | I12: 4.8753377e+09 | J12: 2.0325037e+09 | K12: 4.7609472e+08 | L12: 2.5085985e+09 | M12: 2.366628e+09 | N12: 111264.14 | O12: 2.3667392e+09 | P12: =IF(COUNT(I12,L12,O12)<3,"",I12-L12-O12) -> -4.7683716e-07 | Q12: =IF(COUNT(M12:O12)<3,"",O12-M12-N12) -> 3.4332334e-07 | R12: =L12=K12+J12 -> TRUE | S12: =I12=G12+H12 -> TRUE | T12: 2023年报（官网获取）
A13: 002959 | B13: 小熊电器 | C13: 2023 | D13: 1.5275373e+09 | E13: 1.5706249e+08 | F13: 6.1973941e+08 | G13: 3.8755218e+09 | H13: 1.5107644e+09 | I13: 5.3862862e+09 | J13: 2.1578762e+09 | K13: 4.9197021e+08 | L13: 2.6498464e+09 | M13: 2.7364398e+09 | N13: 0 | O13: 2.7364398e+09 | P13: =IF(COUNT(I13,L13,O13)<3,"",I13-L13-O13) -> 4.7683716e-07 | Q13: =IF(COUNT(M13:O13)<3,"",O13-M13-N13) -> 0 | R13: =L13=K13+J13 -> TRUE | S13: =I13=G13+H13 -> TRUE | T13: 2023年报（官网获取）
... A19: 002705 | B19: 新宝股份 | C19: 2025 | D19: 3.3145578e+09 | E19: 2.1403981e+09 | F19: 1.8965393e+09 | G19: 8143255912 | H19: 7.4710924e+09 | I19: 1.5614348e+10 | J19: 6.5615622e+09 | K19: 3.103132e+08 | L19: 6.8718754e+09 | M19: 8.6278935e+09 | N19: 1.1457937e+08 | O19: 8.7424728e+09 | P19: =IF(COUNT(I19,L19,O19)<3,"",I19-L19-O19) -> 0 | Q19: =IF(COUNT(M19:O19)<3,"",O19-M19-N19) -> -2.9802322e-07 | R19: =L19=K19+J19 -> TRUE | S19: =I19=G19+H19 -> TRUE | T19: 2025年报（官网获取）

Sheet 杜邦速算
A1: 杜邦三因子速算（全公式自动计算，勿改；空白 = 对应年份或上年数据未录入）
A3: 指标 | B3: 公司 | C3: 2021 | D3: 2022 | E3: 2023 | F3: 2024 | G3: 2025
A4: 归母ROE | B4: 苏泊尔 | C4: =IF(OR(SUMIFS(资产负债表!$M:$M,资产负债表!$B:$B,$B4,资产负债表!$C:$C,C$3)=0,SUMIFS(资产负债表!$M:$M,资产负债表!$B:$B,$B4,资产负债表!$C:$C,C$3-1)=0),"",SUMIFS(利润表!$O:$O,利润表!$B:$B,$B4,利润表!$C:$C,C$3)/((SUMIFS(资产负债表!$M:$M,资产负债表!$B:$B,$B4,资产负债表!$C:$C,C$3)+SUMIFS(资产负债表!$M:$M,资产负债表!$B:$B,$B4,资产负债表!$C:$C,C$3-1))/2)) -> 0.26227722 | D4: =IF(OR(SUMIFS(资产负债表!$M:$M,资产负债表!$B:$B,$B4,资产负债表!$C:$C,D$3)=0,SUMIFS(资产负债表!$M:$M,资产负债表!$B:$B,$B4,资产负债表!$C:$C,D$3-1)=0),"",SUMIFS(利润表!$O:$O,利润表!$B:$B,$B4,利润表!$C:$C,D$3)/((SUMIFS(资产负债表!$M:$M,资产负债表!$B:$B,$B4,资产负债表!$C:$C,D$3)+SUMIFS(资产负债表!$M:$M,资产负债表!$B:$B,$B4,资产负债表!$C:$C,D$3-1))/2)) -> 0.28210633 | E4: =IF(OR(SUMIFS(资产负债表!$M:$M,资产负债表!$B:$B,$B4,资产负债表!$C:$C,E$3)=0,SUMIFS(资产负债表!$M:$M,资产负债表!$B:$B,$B4,资产负债表!$C:$C,E$3-1)=0),"",SUMIFS(利润表!$O:$O,利润表!$B:$B,$B4,利润表!$C:$C,E$3)/((SUMIFS(资产负债表!$M:$M,资产负债表!$B:$B,$B4,资产负债表!$C:$C,E$3)+SUMIFS(资产负债表!$M:$M,资产负债表!$B:$B,$B4,资产负债表!$C:$C,E$3-1))/2)) -> 0.32579479 | F4: =IF(OR(SUMIFS(资产负债表!$M:$M,资产负债表!$B:$B,$B4,资产负债表!$C:$C,F$3)=0,SUMIFS(资产负债表!$M:$M,资产负债表!$B:$B,$B4,资产负债表!$C:$C,F$3-1)=0),"",SUMIFS(利润表!$O:$O,利润表!$B:$B,$B4,利润表!$C:$C,F$3)/((SUMIFS(资产负债表!$M:$M,资产负债表!$B:$B,$B4,资产负债表!$C:$C,F$3)+SUMIFS(资产负债表!$M:$M,资产负债表!$B:$B,$B4,资产负债表!$C:$C,F$3-1))/2)) -> 0.35152528 | G4: =IF(OR(SUMIFS(资产负债表!$M:$M,资产负债表!$B:$B,$B4,资产负债表!$C:$C,G$3)=0,SUMIFS(资产负债表!$M:$M,资产负债表!$B:$B,$B4,资产负债表!$C:$C,G$3-1)=0),"",SUMIFS(利润表!$O:$O,利润表!$B:$B,$B4,利润表!$C:$C,G$3)/((SUMIFS(资产负债表!$M:$M,资产负债表!$B:$B,$B4,资产负债表!$C:$C,G$3)+SUMIFS(资产负债表!$M:$M,资产负债表!$B:$B,$B4,资产负债表!$C:$C,G$3-1))/2)) -> 0.32995122
A5: 归母ROE | B5: 九阳股份 | C5: =IF(OR(SUMIFS(资产负债表!$M:$M,资产负债表!$B:$B,$B5,资产负债表!$C:$C,C$3)=0,SUMIFS(资产负债表!$M:$M,资产负债表!$B:$B,$B5,资产负债表!$C:$C,C$3-1)=0),"",SUMIFS(利润表!$O:$O,利润表!$B:$B,$B5,利润表!$C:$C,C$3)/((SUMIFS(资产负债表!$M:$M,资产负债表!$B:$B,$B5,资产负债表!$C:$C,C$3)+SUMIFS(资产负债表!$M:$M,资产负债表!$B:$B,$B5,资产负债表!$C:$C,C$3-1))/2)) | D5: =IF(OR(SUMIFS(资产负债表!$M:$M,资产负债表!$B:$B,$B5,资产负债表!$C:$C,D$3)=0,SUMIFS(资产负债表!$M:$M,资产负债表!$B:$B,$B5,资产负债表!$C:$C,D$3-1)=0),"",SUMIFS(利润表!$O:$O,利润表!$B:$B,$B5,利润表!$C:$C,D$3)/((SUMIFS(资产负债表!$M:$M,资产负债表!$B:$B,$B5,资产负债表!$C:$C,D$3)+SUMIFS(资产负债表!$M:$M,资产负债表!$B:$B,$B5,资产负债表!$C:$C,D$3-1))/2)) | E5: =IF(OR(SUMIFS(资产负债表!$M:$M,资产负债表!$B:$B,$B5,资产负债表!$C:$C,E$3)=0,SUMIFS(资产负债表!$M:$M,资产负债表!$B:$B,$B5,资产负债表!$C:$C,E$3-1)=0),"",SUMIFS(利润表!$O:$O,利润表!$B:$B,$B5,利润表!$C:$C,E$3)/((SUMIFS(资产负债表!$M:$M,资产负债表!$B:$B,$B5,资产负债表!$C:$C,E$3)+SUMIFS(资产负债表!$M:$M,资产负债表!$B:$B,$B5,资产负债表!$C:$C,E$3-1))/2)) -> 0.11467937 | F5: =IF(OR(SUMIFS(资产负债表!$M:$M,资产负债表!$B:$B,$B5,资产负债表!$C:$C,F$3)=0,SUMIFS(资产负债表!$M:$M,资产负债表!$B:$B,$B5,资产负债表!$C:$C,F$3-1)=0),"",SUMIFS(利润表!$O:$O,利润表!$B:$B,$B5,利润表!$C:$C,F$3)/((SUMIFS(资产负债表!$M:$M,资产负债表!$B:$B,$B5,资产负债表!$C:$C,F$3)+SUMIFS(资产负债表!$M:$M,资产负债表!$B:$B,$B5,资产负债表!$C:$C,F$3-1))/2)) -> 0.035172459 | G5: =IF(OR(SUMIFS(资产负债表!$M:$M,资产负债表!$B:$B,$B5,资产负债表!$C:$C,G$3)=0,SUMIFS(资产负债表!$M:$M,资产负债表!$B:$B,$B5,资产负债表!$C:$C,G$3-1)=0),"",SUMIFS(利润表!$O:$O,利润表!$B:$B,$B5,利润表!$C:$C,G$3)/((SUMIFS(资产负债表!$M:$M,资产负债表!$B:$B,$B5,资产负债表!$C:$C,G$3)+SUMIFS(资产负债表!$M:$M,资产负债表!$B:$B,$B5,资产负债表!$C:$C,G$3-1))/2)) -> 0.034005917
A6: 归母ROE | B6: 小熊电器 | C6: =IF(OR(SUMIFS(资产负债表!$M:$M,资产负债表!$B:$B,$B6,资产负债表!$C:$C,C$3)=0,SUMIFS(资产负债表!$M:$M,资产负债表!$B:$B,$B6,资产负债表!$C:$C,C$3-1)=0),"",SUMIFS(利润表!$O:$O,利润表!$B:$B,$B6,利润表!$C:$C,C$3)/((SUMIFS(资产负债表!$M:$M,资产负债表!$B:$B,$B6,资产负债表!$C:$C,C$3)+SUMIFS(资产负债表!$M:$M,资产负债表!$B:$B,$B6,资产负债表!$C:$C,C$3-1))/2)) | D6: =IF(OR(SUMIFS(资产负债表!$M:$M,资产负债表!$B:$B,$B6,资产负债表!$C:$C,D$3)=0,SUMIFS(资产负债表!$M:$M,资产负债表!$B:$B,$B6,资产负债表!$C:$C,D$3-1)=0),"",SUMIFS(利润表!$O:$O,利润表!$B:$B,$B6,利润表!$C:$C,D$3)/((SUMIFS(资产负债表!$M:$M,资产负债表!$B:$B,$B6,资产负债表!$C:$C,D$3)+SUMIFS(资产负债表!$M:$M,资产负债表!$B:$B,$B6,资产负债表!$C:$C,D$3-1))/2)) | E6: =IF(OR(SUMIFS(资产负债表!$M:$M,资产负债表!$B:$B,$B6,资产负债表!$C:$C,E$3)=0,SUMIFS(资产负债表!$M:$M,资产负债表!$B:$B,$B6,资产负债表!$C:$C,E$3-1)=0),"",SUMIFS(利润表!$O:$O,利润表!$B:$B,$B6,利润表!$C:$C,E$3)/((SUMIFS(资产负债表!$M:$M,资产负债表!$B:$B,$B6,资产负债表!$C:$C,E$3)+SUMIFS(资产负债表!$M:$M,资产负债表!$B:$B,$B6,资产负债表!$C:$C,E$3-1))/2)) -> 0.17451193 | F6: =IF(OR(SUMIFS(资产负债表!$M:$M,资产负债表!$B:$B,$B6,资产负债表!$C:$C,F$3)=0,SUMIFS(资产负债表!$M:$M,资产负债表!$B:$B,$B6,资产负债表!$C:$C,F$3-1)=0),"",SUMIFS(利润表!$O:$O,利润表!$B:$B,$B6,利润表!$C:$C,F$3)/((SUMIFS(资产负债表!$M:$M,资产负债表!$B:$B,$B6,资产负债表!$C:$C,F$3)+SUMIFS(资产负债表!$M:$M,资产负债表!$B:$B,$B6,资产负债表!$C:$C,F$3-1))/2)) -> 0.10353889 | G6: =IF(OR(SUMIFS(资产负债表!$M:$M,资产负债表!$B:$B,$B6,资产负债表!$C:$C,G$3)=0,SUMIFS(资产负债表!$M:$M,资产负债表!$B:$B,$B6,资产负债表!$C:$C,G$3-1)=0),"",SUMIFS(利润表!$O:$O,利润表!$B:$B,$B6,利润表!$C:$C,G$3)/((SUMIFS(资产负债表!$M:$M,资产负债表!$B:$B,$B6,资产负债表!$C:$C,G$3)+SUMIFS(资产负债表!$M:$M,资产负债表!$B:$B,$B6,资产负债表!$C:$C,G$3-1))/2)) -> 0.13353906
A7: 归母ROE | B7: 新宝股份 | C7: =IF(OR(SUMIFS(资产负债表!$M:$M,资产负债表!$B:$B,$B7,资产负债表!$C:$C,C$3)=0,SUMIFS(资产负债表!$M:$M,资产负债表!$B:$B,$B7,资产负债表!$C:$C,C$3-1)=0),"",SUMIFS(利润表!$O:$O,利润表!$B:$B,$B7,利润表!$C:$C,C$3)/((SUMIFS(资产负债表!$M:$M,资产负债表!$B:$B,$B7,资产负债表!$C:$C,C$3)+SUMIFS(资产负债表!$M:$M,资产负债表!$B:$B,$B7,资产负债表!$C:$C,C$3-1))/2)) | D7: =IF(OR(SUMIFS(资产负债表!$M:$M,资产负债表!$B:$B,$B7,资产负债表!$C:$C,D$3)=0,SUMIFS(资产负债表!$M:$M,资产负债表!$B:$B,$B7,资产负债表!$C:$C,D$3-1)=0),"",SUMIFS(利润表!$O:$O,利润表!$B:$B,$B7,利润表!$C:$C,D$3)/((SUMIFS(资产负债表!$M:$M,资产负债表!$B:$B,$B7,资产负债表!$C:$C,D$3)+SUMIFS(资产负债表!$M:$M,资产负债表!$B:$B,$B7,资产负债表!$C:$C,D$3-1))/2)) | E7: =IF(OR(SUMIFS(资产负债表!$M:$M,资产负债表!$B:$B,$B7,资产负债表!$C:$C,E$3)=0,SUMIFS(资产负债表!$M:$M,资产负债表!$B:$B,$B7,资产负债表!$C:$C,E$3-1)=0),"",SUMIFS(利润表!$O:$O,利润表!$B:$B,$B7,利润表!$C:$C,E$3)/((SUMIFS(资产负债表!$M:$M,资产负债表!$B:$B,$B7,资产负债表!$C:$C,E$3)+SUMIFS(资产负债表!$M:$M,资产负债表!$B:$B,$B7,资产负债表!$C:$C,E$3-1))/2)) -> 0.13417369 | F7: =IF(OR(SUMIFS(资产负债表!$M:$M,资产负债表!$B:$B,$B7,资产负债表!$C:$C,F$3)=0,SUMIFS(资产负债表!$M:$M,资产负债表!$B:$B,$B7,资产负债表!$C:$C,F$3-1)=0),"",SUMIFS(利润表!$O:$O,利润表!$B:$B,$B7,利润表!$C:$C,F$3)/((SUMIFS(资产负债表!$M:$M,资产负债表!$B:$B,$B7,资产负债表!$C:$C,F$3)+SUMIFS(资产负债表!$M:$M,资产负债表!$B:$B,$B7,资产负债表!$C:$C,F$3-1))/2)) -> 0.13289128 | G7: =IF(OR(SUMIFS(资产负债表!$M:$M,资产负债表!$B:$B,$B7,资产负债表!$C:$C,G$3)=0,SUMIFS(资产负债表!$M:$M,资产负债表!$B:$B,$B7,资产负债表!$C:$C,G$3-1)=0),"",SUMIFS(利润表!$O:$O,利润表!$B:$B,$B7,利润表!$C:$C,G$3)/((SUMIFS(资产负债表!$M:$M,资产负债表!$B:$B,$B7,资产负债表!$C:$C,G$3)+SUMIFS(资产负债表!$M:$M,资产负债表!$B:$B,$B7,资产负债表!$C:$C,G$3-1))/2)) -> 0.11837575
A9: 销售净利率 | B9: 苏泊尔 | C9: =IF(SUMIFS(利润表!$D:$D,利润表!$B:$B,$B9,利润表!$C:$C,C$3)=0,"",SUMIFS(利润表!$O:$O,利润表!$B:$B,$B9,利润表!$C:$C,C$3)/SUMIFS(利润表!$D:$D,利润表!$B:$B,$B9,利润表!$C:$C,C$3)) -> 0.090058548 | D9: =IF(SUMIFS(利润表!$D:$D,利润表!$B:$B,$B9,利润表!$C:$C,D$3)=0,"",SUMIFS(利润表!$O:$O,利润表!$B:$B,$B9,利润表!$C:$C,D$3)/SUMIFS(利润表!$D:$D,利润表!$B:$B,$B9,利润表!$C:$C,D$3)) -> 0.10250895 | E9: =IF(SUMIFS(利润表!$D:$D,利润表!$B:$B,$B9,利润表!$C:$C,E$3)=0,"",SUMIFS(利润表!$O:$O,利润表!$B:$B,$B9,利润表!$C:$C,E$3)/SUMIFS(利润表!$D:$D,利润表!$B:$B,$B9,利润表!$C:$C,E$3)) -> 0.10231897 | F9: =IF(SUMIFS(利润表!$D:$D,利润表!$B:$B,$B9,利润表!$C:$C,F$3)=0,"",SUMIFS(利润表!$O:$O,利润表!$B:$B,$B9,利润表!$C:$C,F$3)/SUMIFS(利润表!$D:$D,利润表!$B:$B,$B9,利润表!$C:$C,F$3)) -> 0.10007628 | G9: =IF(SUMIFS(利润表!$D:$D,利润表!$B:$B,$B9,利润表!$C:$C,G$3)=0,"",SUMIFS(利润表!$O:$O,利润表!$B:$B,$B9,利润表!$C:$C,G$3)/SUMIFS(利润表!$D:$D,利润表!$B:$B,$B9,利润表!$C:$C,G$3)) -> 0.092075484
A10: 销售净利率 | B10: 九阳股份 | C10: =IF(SUMIFS(利润表!$D:$D,利润表!$B:$B,$B10,利润表!$C:$C,C$3)=0,"",SUMIFS(利润表!$O:$O,利润表!$B:$B,$B10,利润表!$C:$C,C$3)/SUMIFS(利润表!$D:$D,利润表!$B:$B,$B10,利润表!$C:$C,C$3)) | D10: =IF(SUMIFS(利润表!$D:$D,利润表!$B:$B,$B10,利润表!$C:$C,D$3)=0,"",SUMIFS(利润表!$O:$O,利润表!$B:$B,$B10,利润表!$C:$C,D$3)/SUMIFS(利润表!$D:$D,利润表!$B:$B,$B10,利润表!$C:$C,D$3)) | E10: =IF(SUMIFS(利润表!$D:$D,利润表!$B:$B,$B10,利润表!$C:$C,E$3)=0,"",SUMIFS(利润表!$O:$O,利润表!$B:$B,$B10,利润表!$C:$C,E$3)/SUMIFS(利润表!$D:$D,利润表!$B:$B,$B10,利润表!$C:$C,E$3)) -> 0.040471728 | F10: =IF(SUMIFS(利润表!$D:$D,利润表!$B:$B,$B10,利润表!$C:$C,F$3)=0,"",SUMIFS(利润表!$O:$O,利润表!$B:$B,$B10,利润表!$C:$C,F$3)/SUMIFS(利润表!$D:$D,利润表!$B:$B,$B10,利润表!$C:$C,F$3)) -> 0.013826118 | G10: =IF(SUMIFS(利润表!$D:$D,利润表!$B:$B,$B10,利润表!$C:$C,G$3)=0,"",SUMIFS(利润表!$O:$O,利润表!$B:$B,$B10,利润表!$C:$C,G$3)/SUMIFS(利润表!$D:$D,利润表!$B:$B,$B10,利润表!$C:$C,G$3)) -> 0.014329987
A11: 销售净利率 | B11: 小熊电器 | C11: =IF(SUMIFS(利润表!$D:$D,利润表!$B:$B,$B11,利润表!$C:$C,C$3)=0,"",SUMIFS(利润表!$O:$O,利润表!$B:$B,$B11,利润表!$C:$C,C$3)/SUMIFS(利润表!$D:$D,利润表!$B:$B,$B11,利润表!$C:$C,C$3)) | D11: =IF(SUMIFS(利润表!$D:$D,利润表!$B:$B,$B11,利润表!$C:$C,D$3)=0,"",SUMIFS(利润表!$O:$O,利润表!$B:$B,$B11,利润表!$C:$C,D$3)/SUMIFS(利润表!$D:$D,利润表!$B:$B,$B11,利润表!$C:$C,D$3)) | E11: =IF(SUMIFS(利润表!$D:$D,利润表!$B:$B,$B11,利润表!$C:$C,E$3)=0,"",SUMIFS(利润表!$O:$O,利润表!$B:$B,$B11,利润表!$C:$C,E$3)/SUMIFS(利润表!$D:$D,利润表!$B:$B,$B11,利润表!$C:$C,E$3)) -> 0.094499945 | F11: =IF(SUMIFS(利润表!$D:$D,利润表!$B:$B,$B11,利润表!$C:$C,F$3)=0,"",SUMIFS(利润表!$O:$O,利润表!$B:$B,$B11,利润表!$C:$C,F$3)/SUMIFS(利润表!$D:$D,利润表!$B:$B,$B11,利润表!$C:$C,F$3)) -> 0.060481512 | G11: =IF(SUMIFS(利润表!$D:$D,利润表!$B:$B,$B11,利润表!$C:$C,G$3)=0,"",SUMIFS(利润表!$O:$O,利润表!$B:$B,$B11,利润表!$C:$C,G$3)/SUMIFS(利润表!$D:$D,利润表!$B:$B,$B11,利润表!$C:$C,G$3)) -> 0.075054473
A12: 销售净利率 | B12: 新宝股份 | C12: =IF(SUMIFS(利润表!$D:$D,利润表!$B:$B,$B12,利润表!$C:$C,C$3)=0,"",SUMIFS(利润表!$O:$O,利润表!$B:$B,$B12,利润表!$C:$C,C$3)/SUMIFS(利润表!$D:$D,利润表!$B:$B,$B12,利润表!$C:$C,C$3)) | D12: =IF(SUMIFS(利润表!$D:$D,利润表!$B:$B,$B12,利润表!$C:$C,D$3)=0,"",SUMIFS(利润表!$O:$O,利润表!$B:$B,$B12,利润表!$C:$C,D$3)/SUMIFS(利润表!$D:$D,利润表!$B:$B,$B12,利润表!$C:$C,D$3)) | E12: =IF(SUMIFS(利润表!$D:$D,利润表!$B:$B,$B12,利润表!$C:$C,E$3)=0,"",SUMIFS(利润表!$O:$O,利润表!$B:$B,$B12,利润表!$C:$C,E$3)/SUMIFS(利润表!$D:$D,利润表!$B:$B,$B12,利润表!$C:$C,E$3)) -> 0.066713784 | F12: =IF(SUMIFS(利润表!$D:$D,利润表!$B:$B,$B12,利润表!$C:$C,F$3)=0,"",SUMIFS(利润表!$O:$O,利润表!$B:$B,$B12,利润表!$C:$C,F$3)/SUMIFS(利润表!$D:$D,利润表!$B:$B,$B12,利润表!$C:$C,F$3)) -> 0.062590551 | G12: =IF(SUMIFS(利润表!$D:$D,利润表!$B:$B,$B12,利润表!$C:$C,G$3)=0,"",SUMIFS(利润表!$O:$O,利润表!$B:$B,$B12,利润表!$C:$C,G$3)/SUMIFS(利润表!$D:$D,利润表!$B:$B,$B12,利润表!$C:$C,G$3)) -> 0.061719702
A14: 总资产周转率(次) | B14: 苏泊尔 | C14: =IF(OR(SUMIFS(资产负债表!$I:$I,资产负债表!$B:$B,$B14,资产负债表!$C:$C,C$3)=0,SUMIFS(资产负债表!$I:$I,资产负债表!$B:$B,$B14,资产负债表!$C:$C,C$3-1)=0),"",SUMIFS(利润表!$D:$D,利润表!$B:$B,$B14,利润表!$C:$C,C$3)/((SUMIFS(资产负债表!$I:$I,资产负债表!$B:$B,$B14,资产负债表!$C:$C,C$3)+SUMIFS(资产负债表!$I:$I,资产负债表!$B:$B,$B14,资产负债表!$C:$C,C$3-1))/2)) -> 1.6482557 | D14: =IF(OR(SUMIFS(资产负债表!$I:$I,资产负债表!$B:$B,$B14,资产负债表!$C:$C,D$3)=0,SUMIFS(资产负债表!$I:$I,资产负债表!$B:$B,$B14,资产负债表!$C:$C,D$3-1)=0),"",SUMIFS(利润表!$D:$D,利润表!$B:$B,$B14,利润表!$C:$C,D$3)/((SUMIFS(资产负债表!$I:$I,资产负债表!$B:$B,$B14,资产负债表!$C:$C,D$3)+SUMIFS(资产负债表!$I:$I,资产负债表!$B:$B,$B14,资产负债表!$C:$C,D$3-1))/2)) -> 1.502342 | E14: =IF(OR(SUMIFS(资产负债表!$I:$I,资产负债表!$B:$B,$B14,资产负债表!$C:$C,E$3)=0,SUMIFS(资产负债表!$I:$I,资产负债表!$B:$B,$B14,资产负债表!$C:$C,E$3-1)=0),"",SUMIFS(利润表!$D:$D,利润表!$B:$B,$B14,利润表!$C:$C,E$3)/((SUMIFS(资产负债表!$I:$I,资产负债表!$B:$B,$B14,资产负债表!$C:$C,E$3)+SUMIFS(资产负债表!$I:$I,资产负债表!$B:$B,$B14,资产负债表!$C:$C,E$3-1))/2)) -> 1.6350324 | F14: =IF(OR(SUMIFS(资产负债表!$I:$I,资产负债表!$B:$B,$B14,资产负债表!$C:$C,F$3)=0,SUMIFS(资产负债表!$I:$I,资产负债表!$B:$B,$B14,资产负债表!$C:$C,F$3-1)=0),"",SUMIFS(利润表!$D:$D,利润表!$B:$B,$B14,利润表!$C:$C,F$3)/((SUMIFS(资产负债表!$I:$I,资产负债表!$B:$B,$B14,资产负债表!$C:$C,F$3)+SUMIFS(资产负债表!$I:$I,资产负债表!$B:$B,$B14,资产负债表!$C:$C,F$3-1))/2)) -> 1.7008085 | G14: =IF(OR(SUMIFS(资产负债表!$I:$I,资产负债表!$B:$B,$B14,资产负债表!$C:$C,G$3)=0,SUMIFS(资产负债表!$I:$I,资产负债表!$B:$B,$B14,资产负债表!$C:$C,G$3-1)=0),"",SUMIFS(利润表!$D:$D,利润表!$B:$B,$B14,利润表!$C:$C,G$3)/((SUMIFS(资产负债表!$I:$I,资产负债表!$B:$B,$B14,资产负债表!$C:$C,G$3)+SUMIFS(资产负债表!$I:$I,资产负债表!$B:$B,$B14,资产负债表!$C:$C,G$3-1))/2)) -> 1.7068468
A15: 总资产周转率(次) | B15: 九阳股份 | C15: =IF(OR(SUMIFS(资产负债表!$I:$I,资产负债表!$B:$B,$B15,资产负债表!$C:$C,C$3)=0,SUMIFS(资产负债表!$I:$I,资产负债表!$B:$B,$B15,资产负债表!$C:$C,C$3-1)=0),"",SUMIFS(利润表!$D:$D,利润表!$B:$B,$B15,利润表!$C:$C,C$3)/((SUMIFS(资产负债表!$I:$I,资产负债表!$B:$B,$B15,资产负债表!$C:$C,C$3)+SUMIFS(资产负债表!$I:$I,资产负债表!$B:$B,$B15,资产负债表!$C:$C,C$3-1))/2)) | D15: =IF(OR(SUMIFS(资产负债表!$I:$I,资产负债表!$B:$B,$B15,资产负债表!$C:$C,D$3)=0,SUMIFS(资产负债表!$I:$I,资产负债表!$B:$B,$B15,资产负债表!$C:$C,D$3-1)=0),"",SUMIFS(利润表!$D:$D,利润表!$B:$B,$B15,利润表!$C:$C,D$3)/((SUMIFS(资产负债表!$I:$I,资产负债表!$B:$B,$B15,资产负债表!$C:$C,D$3)+SUMIFS(资产负债表!$I:$I,资产负债表!$B:$B,$B15,资产负债表!$C:$C,D$3-1))/2)) | E15: =IF(OR(SUMIFS(资产负债表!$I:$I,资产负债表!$B:$B,$B15,资产负债表!$C:$C,E$3)=0,SUMIFS(资产负债表!$I:$I,资产负债表!$B:$B,$B15,资产负债表!$C:$C,E$3-1)=0),"",SUMIFS(利润表!$D:$D,利润表!$B:$B,$B15,利润表!$C:$C,E$3)/((SUMIFS(资产负债表!$I:$I,资产负债表!$B:$B,$B15,资产负债表!$C:$C,E$3)+SUMIFS(资产负债表!$I:$I,资产负债表!$B:$B,$B15,资产负债表!$C:$C,E$3-1))/2)) -> 1.3089881 | F15: =IF(OR(SUMIFS(资产负债表!$I:$I,资产负债表!$B:$B,$B15,资产负债表!$C:$C,F$3)=0,SUMIFS(资产负债表!$I:$I,资产负债表!$B:$B,$B15,资产负债表!$C:$C,F$3-1)=0),"",SUMIFS(利润表!$D:$D,利润表!$B:$B,$B15,利润表!$C:$C,F$3)/((SUMIFS(资产负债表!$I:$I,资产负债表!$B:$B,$B15,资产负债表!$C:$C,F$3)+SUMIFS(资产负债表!$I:$I,资产负债表!$B:$B,$B15,资产负债表!$C:$C,F$3-1))/2)) -> 1.1645164 | G15: =IF(OR(SUMIFS(资产负债表!$I:$I,资产负债表!$B:$B,$B15,资产负债表!$C:$C,G$3)=0,SUMIFS(资产负债表!$I:$I,资产负债表!$B:$B,$B15,资产负债表!$C:$C,G$3-1)=0),"",SUMIFS(利润表!$D:$D,利润表!$B:$B,$B15,利润表!$C:$C,G$3)/((SUMIFS(资产负债表!$I:$I,资产负债表!$B:$B,$B15,资产负债表!$C:$C,G$3)+SUMIFS(资产负债表!$I:$I,资产负债表!$B:$B,$B15,资产负债表!$C:$C,G$3-1))/2)) -> 1.067561
A16: 总资产周转率(次) | B16: 小熊电器 | C16: =IF(OR(SUMIFS(资产负债表!$I:$I,资产负债表!$B:$B,$B16,资产负债表!$C:$C,C$3)=0,SUMIFS(资产负债表!$I:$I,资产负债表!$B:$B,$B16,资产负债表!$C:$C,C$3-1)=0),"",SUMIFS(利润表!$D:$D,利润表!$B:$B,$B16,利润表!$C:$C,C$3)/((SUMIFS(资产负债表!$I:$I,资产负债表!$B:$B,$B16,资产负债表!$C:$C,C$3)+SUMIFS(资产负债表!$I:$I,资产负债表!$B:$B,$B16,资产负债表!$C:$C,C$3-1))/2)) | D16: =IF(OR(SUMIFS(资产负债表!$I:$I,资产负债表!$B:$B,$B16,资产负债表!$C:$C,D$3)=0,SUMIFS(资产负债表!$I:$I,资产负债表!$B:$B,$B16,资产负债表!$C:$C,D$3-1)=0),"",SUMIFS(利润表!$D:$D,利润表!$B:$B,$B16,利润表!$C:$C,D$3)/((SUMIFS(资产负债表!$I:$I,资产负债表!$B:$B,$B16,资产负债表!$C:$C,D$3)+SUMIFS(资产负债表!$I:$I,资产负债表!$B:$B,$B16,资产负债表!$C:$C,D$3-1))/2)) | E16: =IF(OR(SUMIFS(资产负债表!$I:$I,资产负债表!$B:$B,$B16,资产负债表!$C:$C,E$3)=0,SUMIFS(资产负债表!$I:$I,资产负债表!$B:$B,$B16,资产负债表!$C:$C,E$3-1)=0),"",SUMIFS(利润表!$D:$D,利润表!$B:$B,$B16,利润表!$C:$C,E$3)/((SUMIFS(资产负债表!$I:$I,资产负债表!$B:$B,$B16,资产负债表!$C:$C,E$3)+SUMIFS(资产负债表!$I:$I,资产负债表!$B:$B,$B16,资产负债表!$C:$C,E$3-1))/2)) -> 0.91835122 | F16: =IF(OR(SUMIFS(资产负债表!$I:$I,资产负债表!$B:$B,$B16,资产负债表!$C:$C,F$3)=0,SUMIFS(资产负债表!$I:$I,资产负债表!$B:$B,$B16,资产负债表!$C:$C,F$3-1)=0),"",SUMIFS(利润表!$D:$D,利润表!$B:$B,$B16,利润表!$C:$C,F$3)/((SUMIFS(资产负债表!$I:$I,资产负债表!$B:$B,$B16,资产负债表!$C:$C,F$3)+SUMIFS(资产负债表!$I:$I,资产负债表!$B:$B,$B16,资产负债表!$C:$C,F$3-1))/2)) -> 0.82466695 | G16: =IF(OR(SUMIFS(资产负债表!$I:$I,资产负债表!$B:$B,$B16,资产负债表!$C:$C,G$3)=0,SUMIFS(资产负债表!$I:$I,资产负债表!$B:$B,$B16,资产负债表!$C:$C,G$3-1)=0),"",SUMIFS(利润表!$D:$D,利润表!$B:$B,$B16,利润表!$C:$C,G$3)/((SUMIFS(资产负债表!$I:$I,资产负债表!$B:$B,$B16,资产负债表!$C:$C,G$3)+SUMIFS(资产负债表!$I:$I,资产负债表!$B:$B,$B16,资产负债表!$C:$C,G$3-1))/2)) -> 0.8722834
A17: 总资产周转率(次) | B17: 新宝股份 | C17: =IF(OR(SUMIFS(资产负债表!$I:$I,资产负债表!$B:$B,$B17,资产负债表!$C:$C,C$3)=0,SUMIFS(资产负债表!$I:$I,资产负债表!$B:$B,$B17,资产负债表!$C:$C,C$3-1)=0),"",SUMIFS(利润表!$D:$D,利润表!$B:$B,$B17,利润表!$C:$C,C$3)/((SUMIFS(资产负债表!$I:$I,资产负债表!$B:$B,$B17,资产负债表!$C:$C,C$3)+SUMIFS(资产负债表!$I:$I,资产负债表!$B:$B,$B17,资产负债表!$C:$C,C$3-1))/2)) | D17: =IF(OR(SUMIFS(资产负债表!$I:$I,资产负债表!$B:$B,$B17,资产负债表!$C:$C,D$3)=0,SUMIFS(资产负债表!$I:$I,资产负债表!$B:$B,$B17,资产负债表!$C:$C,D$3-1)=0),"",SUMIFS(利润表!$D:$D,利润表!$B:$B,$B17,利润表!$C:$C,D$3)/((SUMIFS(资产负债表!$I:$I,资产负债表!$B:$B,$B17,资产负债表!$C:$C,D$3)+SUMIFS(资产负债表!$I:$I,资产负债表!$B:$B,$B17,资产负债表!$C:$C,D$3-1))/2)) | E17: =IF(OR(SUMIFS(资产负债表!$I:$I,资产负债表!$B:$B,$B17,资产负债表!$C:$C,E$3)=0,SUMIFS(资产负债表!$I:$I,资产负债表!$B:$B,$B17,资产负债表!$C:$C,E$3-1)=0),"",SUMIFS(利润表!$D:$D,利润表!$B:$B,$B17,利润表!$C:$C,E$3)/((SUMIFS(资产负债表!$I:$I,资产负债表!$B:$B,$B17,资产负债表!$C:$C,E$3)+SUMIFS(资产负债表!$I:$I,资产负债表!$B:$B,$B17,资产负债表!$C:$C,E$3-1))/2)) -> 1.0728017 | F17: =IF(OR(SUMIFS(资产负债表!$I:$I,资产负债表!$B:$B,$B17,资产负债表!$C:$C,F$3)=0,SUMIFS(资产负债表!$I:$I,资产负债表!$B:$B,$B17,资产负债表!$C:$C,F$3-1)=0),"",SUMIFS(利润表!$D:$D,利润表!$B:$B,$B17,利润表!$C:$C,F$3)/((SUMIFS(资产负债表!$I:$I,资产负债表!$B:$B,$B17,资产负债表!$C:$C,F$3)+SUMIFS(资产负债表!$I:$I,资产负债表!$B:$B,$B17,资产负债表!$C:$C,F$3-1))/2)) -> 1.1185845 | G17: =IF(OR(SUMIFS(资产负债表!$I:$I,资产负债表!$B:$B,$B17,资产负债表!$C:$C,G$3)=0,SUMIFS(资产负债表!$I:$I,资产负债表!$B:$B,$B17,资产负债表!$C:$C,G$3-1)=0),"",SUMIFS(利润表!$D:$D,利润表!$B:$B,$B17,利润表!$C:$C,G$3)/((SUMIFS(资产负债表!$I:$I,资产负债表!$B:$B,$B17,资产负债表!$C:$C,G$3)+SUMIFS(资产负债表!$I:$I,资产负债表!$B:$B,$B17,资产负债表!$C:$C,G$3-1))/2)) -> 1.0360086
A19: 权益乘数(倍) | B19: 苏泊尔 | C19: =IF(OR(SUMIFS(资产负债表!$I:$I,资产负债表!$B:$B,$B19,资产负债表!$C:$C,C$3)=0,SUMIFS(资产负债表!$I:$I,资产负债表!$B:$B,$B19,资产负债表!$C:$C,C$3-1)=0,SUMIFS(资产负债表!$M:$M,资产负债表!$B:$B,$B19,资产负债表!$C:$C,C$3)=0,SUMIFS(资产负债表!$M:$M,资产负债表!$B:$B,$B19,资产负债表!$C:$C,C$3-1)=0),"",((SUMIFS(资产负债表!$I:$I,资产负债表!$B:$B,$B19,资产负债表!$C:$C,C$3)+SUMIFS(资产负债表!$I:$I,资产负债表!$B:$B,$B19,资产负债表!$C:$C,C$3-1))/2)/((SUMIFS(资产负债表!$M:$M,资产负债表!$B:$B,$B19,资产负债表!$C:$C,C$3)+SUMIFS(资产负债表!$M:$M,资产负债表!$B:$B,$B19,资产负债表!$C:$C,C$3-1))/2)) -> 1.7668962 | D19: =IF(OR(SUMIFS(资产负债表!$I:$I,资产负债表!$B:$B,$B19,资产负债表!$C:$C,D$3)=0,SUMIFS(资产负债表!$I:$I,资产负债表!$B:$B,$B19,资产负债表!$C:$C,D$3-1)=0,SUMIFS(资产负债表!$M:$M,资产负债表!$B:$B,$B19,资产负债表!$C:$C,D$3)=0,SUMIFS(资产负债表!$M:$M,资产负债表!$B:$B,$B19,资产负债表!$C:$C,D$3-1)=0),"",((SUMIFS(资产负债表!$I:$I,资产负债表!$B:$B,$B19,资产负债表!$C:$C,D$3)+SUMIFS(资产负债表!$I:$I,资产负债表!$B:$B,$B19,资产负债表!$C:$C,D$3-1))/2)/((SUMIFS(资产负债表!$M:$M,资产负债表!$B:$B,$B19,资产负债表!$C:$C,D$3)+SUMIFS(资产负债表!$M:$M,资产负债表!$B:$B,$B19,资产负债表!$C:$C,D$3-1))/2)) -> 1.8318178 | E19: =IF(OR(SUMIFS(资产负债表!$I:$I,资产负债表!$B:$B,$B19,资产负债表!$C:$C,E$3)=0,SUMIFS(资产负债表!$I:$I,资产负债表!$B:$B,$B19,资产负债表!$C:$C,E$3-1)=0,SUMIFS(资产负债表!$M:$M,资产负债表!$B:$B,$B19,资产负债表!$C:$C,E$3)=0,SUMIFS(资产负债表!$M:$M,资产负债表!$B:$B,$B19,资产负债表!$C:$C,E$3-1)=0),"",((SUMIFS(资产负债表!$I:$I,资产负债表!$B:$B,$B19,资产负债表!$C:$C,E$3)+SUMIFS(资产负债表!$I:$I,资产负债表!$B:$B,$B19,资产负债表!$C:$C,E$3-1))/2)/((SUMIFS(资产负债表!$M:$M,资产负债表!$B:$B,$B19,资产负债表!$C:$C,E$3)+SUMIFS(资产负债表!$M:$M,资产负债表!$B:$B,$B19,资产负债表!$C:$C,E$3-1))/2)) -> 1.9474289 | F19: =IF(OR(SUMIFS(资产负债表!$I:$I,资产负债表!$B:$B,$B19,资产负债表!$C:$C,F$3)=0,SUMIFS(资产负债表!$I:$I,资产负债表!$B:$B,$B19,资产负债表!$C:$C,F$3-1)=0,SUMIFS(资产负债表!$M:$M,资产负债表!$B:$B,$B19,资产负债表!$C:$C,F$3)=0,SUMIFS(资产负债表!$M:$M,资产负债表!$B:$B,$B19,资产负债表!$C:$C,F$3-1)=0),"",((SUMIFS(资产负债表!$I:$I,资产负债表!$B:$B,$B19,资产负债表!$C:$C,F$3)+SUMIFS(资产负债表!$I:$I,资产负债表!$B:$B,$B19,资产负债表!$C:$C,F$3-1))/2)/((SUMIFS(资产负债表!$M:$M,资产负债表!$B:$B,$B19,资产负债表!$C:$C,F$3)+SUMIFS(资产负债表!$M:$M,资产负债表!$B:$B,$B19,资产负债表!$C:$C,F$3-1))/2)) -> 2.0652374 | G19: =IF(OR(SUMIFS(资产负债表!$I:$I,资产负债表!$B:$B,$B19,资产负债表!$C:$C,G$3)=0,SUMIFS(资产负债表!$I:$I,资产负债表!$B:$B,$B19,资产负债表!$C:$C,G$3-1)=0,SUMIFS(资产负债表!$M:$M,资产负债表!$B:$B,$B19,资产负债表!$C:$C,G$3)=0,SUMIFS(资产负债表!$M:$M,资产负债表!$B:$B,$B19,资产负债表!$C:$C,G$3-1)=0),"",((SUMIFS(资产负债表!$I:$I,资产负债表!$B:$B,$B19,资产负债表!$C:$C,G$3)+SUMIFS(资产负债表!$I:$I,资产负债表!$B:$B,$B19,资产负债表!$C:$C,G$3-1))/2)/((SUMIFS(资产负债表!$M:$M,资产负债表!$B:$B,$B19,资产负债表!$C:$C,G$3)+SUMIFS(资产负债表!$M:$M,资产负债表!$B:$B,$B19,资产负债表!$C:$C,G$3-1))/2)) -> 2.0994773
A20: 权益乘数(倍) | B20: 九阳股份 | C20: =IF(OR(SUMIFS(资产负债表!$I:$I,资产负债表!$B:$B,$B20,资产负债表!$C:$C,C$3)=0,SUMIFS(资产负债表!$I:$I,资产负债表!$B:$B,$B20,资产负债表!$C:$C,C$3-1)=0,SUMIFS(资产负债表!$M:$M,资产负债表!$B:$B,$B20,资产负债表!$C:$C,C$3)=0,SUMIFS(资产负债表!$M:$M,资产负债表!$B:$B,$B20,资产负债表!$C:$C,C$3-1)=0),"",((SUMIFS(资产负债表!$I:$I,资产负债表!$B:$B,$B20,资产负债表!$C:$C,C$3)+SUMIFS(资产负债表!$I:$I,资产负债表!$B:$B,$B20,资产负债表!$C:$C,C$3-1))/2)/((SUMIFS(资产负债表!$M:$M,资产负债表!$B:$B,$B20,资产负债表!$C:$C,C$3)+SUMIFS(资产负债表!$M:$M,资产负债表!$B:$B,$B20,资产负债表!$C:$C,C$3-1))/2)) | D20: =IF(OR(SUMIFS(资产负债表!$I:$I,资产负债表!$B:$B,$B20,资产负债表!$C:$C,D$3)=0,SUMIFS(资产负债表!$I:$I,资产负债表!$B:$B,$B20,资产负债表!$C:$C,D$3-1)=0,SUMIFS(资产负债表!$M:$M,资产负债表!$B:$B,$B20,资产负债表!$C:$C,D$3)=0,SUMIFS(资产负债表!$M:$M,资产负债表!$B:$B,$B20,资产负债表!$C:$C,D$3-1)=0),"",((SUMIFS(资产负债表!$I:$I,资产负债表!$B:$B,$B20,资产负债表!$C:$C,D$3)+SUMIFS(资产负债表!$I:$I,资产负债表!$B:$B,$B20,资产负债表!$C:$C,D$3-1))/2)/((SUMIFS(资产负债表!$M:$M,资产负债表!$B:$B,$B20,资产负债表!$C:$C,D$3)+SUMIFS(资产负债表!$M:$M,资产负债表!$B:$B,$B20,资产负债表!$C:$C,D$3-1))/2)) | E20: =IF(OR(SUMIFS(资产负债表!$I:$I,资产负债表!$B:$B,$B20,资产负债表!$C:$C,E$3)=0,SUMIFS(资产负债表!$I:$I,资产负债表!$B:$B,$B20,资产负债表!$C:$C,E$3-1)=0,SUMIFS(资产负债表!$M:$M,资产负债表!$B:$B,$B20,资产负债表!$C:$C,E$3)=0,SUMIFS(资产负债表!$M:$M,资产负债表!$B:$B,$B20,资产负债表!$C:$C,E$3-1)=0),"",((SUMIFS(资产负债表!$I:$I,资产负债表!$B:$B,$B20,资产负债表!$C:$C,E$3)+SUMIFS(资产负债表!$I:$I,资产负债表!$B:$B,$B20,资产负债表!$C:$C,E$3-1))/2)/((SUMIFS(资产负债表!$M:$M,资产负债表!$B:$B,$B20,资产负债表!$C:$C,E$3)+SUMIFS(资产负债表!$M:$M,资产负债表!$B:$B,$B20,资产负债表!$C:$C,E$3-1))/2)) -> 2.1647008 | F20: =IF(OR(SUMIFS(资产负债表!$I:$I,资产负债表!$B:$B,$B20,资产负债表!$C:$C,F$3)=0,SUMIFS(资产负债表!$I:$I,资产负债表!$B:$B,$B20,资产负债表!$C:$C,F$3-1)=0,SUMIFS(资产负债表!$M:$M,资产负债表!$B:$B,$B20,资产负债表!$C:$C,F$3)=0,SUMIFS(资产负债表!$M:$M,资产负债表!$B:$B,$B20,资产负债表!$C:$C,F$3-1)=0),"",((SUMIFS(资产负债表!$I:$I,资产负债表!$B:$B,$B20,资产负债表!$C:$C,F$3)+SUMIFS(资产负债表!$I:$I,资产负债表!$B:$B,$B20,资产负债表!$C:$C,F$3-1))/2)/((SUMIFS(资产负债表!$M:$M,资产负债表!$B:$B,$B20,资产负债表!$C:$C,F$3)+SUMIFS(资产负债表!$M:$M,资产负债表!$B:$B,$B20,资产负债表!$C:$C,F$3-1))/2)) -> 2.1845243 | G20: =IF(OR(SUMIFS(资产负债表!$I:$I,资产负债表!$B:$B,$B20,资产负债表!$C:$C,G$3)=0,SUMIFS(资产负债表!$I:$I,资产负债表!$B:$B,$B20,资产负债表!$C:$C,G$3-1)=0,SUMIFS(资产负债表!$M:$M,资产负债表!$B:$B,$B20,资产负债表!$C:$C,G$3)=0,SUMIFS(资产负债表!$M:$M,资产负债表!$B:$B,$B20,资产负债表!$C:$C,G$3-1)=0),"",((SUMIFS(资产负债表!$I:$I,资产负债表!$B:$B,$B20,资产负债表!$C:$C,G$3)+SUMIFS(资产负债表!$I:$I,资产负债表!$B:$B,$B20,资产负债表!$C:$C,G$3-1))/2)/((SUMIFS(资产负债表!$M:$M,资产负债表!$B:$B,$B20,资产负债表!$C:$C,G$3)+SUMIFS(资产负债表!$M:$M,资产负债表!$B:$B,$B20,资产负债表!$C:$C,G$3-1))/2)) -> 2.22288
A21: 权益乘数(倍) | B21: 小熊电器 | C21: =IF(OR(SUMIFS(资产负债表!$I:$I,资产负债表!$B:$B,$B21,资产负债表!$C:$C,C$3)=0,SUMIFS(资产负债表!$I:$I,资产负债表!$B:$B,$B21,资产负债表!$C:$C,C$3-1)=0,SUMIFS(资产负债表!$M:$M,资产负债表!$B:$B,$B21,资产负债表!$C:$C,C$3)=0,SUMIFS(资产负债表!$M:$M,资产负债表!$B:$B,$B21,资产负债表!$C:$C,C$3-1)=0),"",((SUMIFS(资产负债表!$I:$I,资产负债表!$B:$B,$B21,资产负债表!$C:$C,C$3)+SUMIFS(资产负债表!$I:$I,资产负债表!$B:$B,$B21,资产负债表!$C:$C,C$3-1))/2)/((SUMIFS(资产负债表!$M:$M,资产负债表!$B:$B,$B21,资产负债表!$C:$C,C$3)+SUMIFS(资产负债表!$M:$M,资产负债表!$B:$B,$B21,资产负债表!$C:$C,C$3-1))/2)) | D21: =IF(OR(SUMIFS(资产负债表!$I:$I,资产负债表!$B:$B,$B21,资产负债表!$C:$C,D$3)=0,SUMIFS(资产负债表!$I:$I,资产负债表!$B:$B,$B21,资产负债表!$C:$C,D$3-1)=0,SUMIFS(资产负债表!$M:$M,资产负债表!$B:$B,$B21,资产负债表!$C:$C,D$3)=0,SUMIFS(资产负债表!$M:$M,资产负债表!$B:$B,$B21,资产负债表!$C:$C,D$3-1)=0),"",((SUMIFS(资产负债表!$I:$I,资产负债表!$B:$B,$B21,资产负债表!$C:$C,D$3)+SUMIFS(资产负债表!$I:$I,资产负债表!$B:$B,$B21,资产负债表!$C:$C,D$3-1))/2)/((SUMIFS(资产负债表!$M:$M,资产负债表!$B:$B,$B21,资产负债表!$C:$C,D$3)+SUMIFS(资产负债表!$M:$M,资产负债表!$B:$B,$B21,资产负债表!$C:$C,D$3-1))/2)) | E21: =IF(OR(SUMIFS(资产负债表!$I:$I,资产负债表!$B:$B,$B21,资产负债表!$C:$C,E$3)=0,SUMIFS(资产负债表!$I:$I,资产负债表!$B:$B,$B21,资产负债表!$C:$C,E$3-1)=0,SUMIFS(资产负债表!$M:$M,资产负债表!$B:$B,$B21,资产负债表!$C:$C,E$3)=0,SUMIFS(资产负债表!$M:$M,资产负债表!$B:$B,$B21,资产负债表!$C:$C,E$3-1)=0),"",((SUMIFS(资产负债表!$I:$I,资产负债表!$B:$B,$B21,资产负债表!$C:$C,E$3)+SUMIFS(资产负债表!$I:$I,资产负债表!$B:$B,$B21,资产负债表!$C:$C,E$3-1))/2)/((SUMIFS(资产负债表!$M:$M,资产负债表!$B:$B,$B21,资产负债表!$C:$C,E$3)+SUMIFS(资产负债表!$M:$M,资产负债表!$B:$B,$B21,资产负债表!$C:$C,E$3-1))/2)) -> 2.0108735 | F21: =IF(OR(SUMIFS(资产负债表!$I:$I,资产负债表!$B:$B,$B21,资产负债表!$C:$C,F$3)=0,SUMIFS(资产负债表!$I:$I,资产负债表!$B:$B,$B21,资产负债表!$C:$C,F$3-1)=0,SUMIFS(资产负债表!$M:$M,资产负债表!$B:$B,$B21,资产负债表!$C:$C,F$3)=0,SUMIFS(资产负债表!$M:$M,资产负债表!$B:$B,$B21,资产负债表!$C:$C,F$3-1)=0),"",((SUMIFS(资产负债表!$I:$I,资产负债表!$B:$B,$B21,资产负债表!$C:$C,F$3)+SUMIFS(资产负债表!$I:$I,资产负债表!$B:$B,$B21,资产负债表!$C:$C,F$3-1))/2)/((SUMIFS(资产负债表!$M:$M,资产负债表!$B:$B,$B21,资产负债表!$C:$C,F$3)+SUMIFS(资产负债表!$M:$M,资产负债表!$B:$B,$B21,资产负债表!$C:$C,F$3-1))/2)) -> 2.0758801 | G21: =IF(OR(SUMIFS(资产负债表!$I:$I,资产负债表!$B:$B,$B21,资产负债表!$C:$C,G$3)=0,SUMIFS(资产负债表!$I:$I,资产负债表!$B:$B,$B21,资产负债表!$C:$C,G$3-1)=0,SUMIFS(资产负债表!$M:$M,资产负债表!$B:$B,$B21,资产负债表!$C:$C,G$3)=0,SUMIFS(资产负债表!$M:$M,资产负债表!$B:$B,$B21,资产负债表!$C:$C,G$3-1)=0),"",((SUMIFS(资产负债表!$I:$I,资产负债表!$B:$B,$B21,资产负债表!$C:$C,G$3)+SUMIFS(资产负债表!$I:$I,资产负债表!$B:$B,$B21,资产负债表!$C:$C,G$3-1))/2)/((SUMIFS(资产负债表!$M:$M,资产负债表!$B:$B,$B21,资产负债表!$C:$C,G$3)+SUMIFS(资产负债表!$M:$M,资产负债表!$B:$B,$B21,资产负债表!$C:$C,G$3-1))/2)) -> 2.0397368
A22: 权益乘数(倍) | B22: 新宝股份 | C22: =IF(OR(SUMIFS(资产负债表!$I:$I,资产负债表!$B:$B,$B22,资产负债表!$C:$C,C$3)=0,SUMIFS(资产负债表!$I:$I,资产负债表!$B:$B,$B22,资产负债表!$C:$C,C$3-1)=0,SUMIFS(资产负债表!$M:$M,资产负债表!$B:$B,$B22,资产负债表!$C:$C,C$3)=0,SUMIFS(资产负债表!$M:$M,资产负债表!$B:$B,$B22,资产负债表!$C:$C,C$3-1)=0),"",((SUMIFS(资产负债表!$I:$I,资产负债表!$B:$B,$B22,资产负债表!$C:$C,C$3)+SUMIFS(资产负债表!$I:$I,资产负债表!$B:$B,$B22,资产负债表!$C:$C,C$3-1))/2)/((SUMIFS(资产负债表!$M:$M,资产负债表!$B:$B,$B22,资产负债表!$C:$C,C$3)+SUMIFS(资产负债表!$M:$M,资产负债表!$B:$B,$B22,资产负债表!$C:$C,C$3-1))/2)) | D22: =IF(OR(SUMIFS(资产负债表!$I:$I,资产负债表!$B:$B,$B22,资产负债表!$C:$C,D$3)=0,SUMIFS(资产负债表!$I:$I,资产负债表!$B:$B,$B22,资产负债表!$C:$C,D$3-1)=0,SUMIFS(资产负债表!$M:$M,资产负债表!$B:$B,$B22,资产负债表!$C:$C,D$3)=0,SUMIFS(资产负债表!$M:$M,资产负债表!$B:$B,$B22,资产负债表!$C:$C,D$3-1)=0),"",((SUMIFS(资产负债表!$I:$I,资产负债表!$B:$B,$B22,资产负债表!$C:$C,D$3)+SUMIFS(资产负债表!$I:$I,资产负债表!$B:$B,$B22,资产负债表!$C:$C,D$3-1))/2)/((SUMIFS(资产负债表!$M:$M,资产负债表!$B:$B,$B22,资产负债表!$C:$C,D$3)+SUMIFS(资产负债表!$M:$M,资产负债表!$B:$B,$B22,资产负债表!$C:$C,D$3-1))/2)) | E22: =IF(OR(SUMIFS(资产负债表!$I:$I,资产负债表!$B:$B,$B22,资产负债表!$C:$C,E$3)=0,SUMIFS(资产负债表!$I:$I,资产负债表!$B:$B,$B22,资产负债表!$C:$C,E$3-1)=0,SUMIFS(资产负债表!$M:$M,资产负债表!$B:$B,$B22,资产负债表!$C:$C,E$3)=0,SUMIFS(资产负债表!$M:$M,资产负债表!$B:$B,$B22,资产负债表!$C:$C,E$3-1)=0),"",((SUMIFS(资产负债表!$I:$I,资产负债表!$B:$B,$B22,资产负债表!$C:$C,E$3)+SUMIFS(资产负债表!$I:$I,资产负债表!$B:$B,$B22,资产负债表!$C:$C,E$3-1))/2)/((SUMIFS(资产负债表!$M:$M,资产负债表!$B:$B,$B22,资产负债表!$C:$C,E$3)+SUMIFS(资产负债表!$M:$M,资产负债表!$B:$B,$B22,资产负债表!$C:$C,E$3-1))/2)) -> 1.8747024 | F22: =IF(OR(SUMIFS(资产负债表!$I:$I,资产负债表!$B:$B,$B22,资产负债表!$C:$C,F$3)=0,SUMIFS(资产负债表!$I:$I,资产负债表!$B:$B,$B22,资产负债表!$C:$C,F$3-1)=0,SUMIFS(资产负债表!$M:$M,资产负债表!$B:$B,$B22,资产负债表!$C:$C,F$3)=0,SUMIFS(资产负债表!$M:$M,资产负债表!$B:$B,$B22,资产负债表!$C:$C,F$3-1)=0),"",((SUMIFS(资产负债表!$I:$I,资产负债表!$B:$B,$B22,资产负债表!$C:$C,F$3)+SUMIFS(资产负债表!$I:$I,资产负债表!$B:$B,$B22,资产负债表!$C:$C,F$3-1))/2)/((SUMIFS(资产负债表!$M:$M,资产负债表!$B:$B,$B22,资产负债表!$C:$C,F$3)+SUMIFS(资产负债表!$M:$M,资产负债表!$B:$B,$B22,资产负债表!$C:$C,F$3-1))/2)) -> 1.8980993 | G22: =IF(OR(SUMIFS(资产负债表!$I:$I,资产负债表!$B:$B,$B22,资产负债表!$C:$C,G$3)=0,SUMIFS(资产负债表!$I:$I,资产负债表!$B:$B,$B22,资产负债表!$C:$C,G$3-1)=0,SUMIFS(资产负债表!$M:$M,资产负债表!$B:$B,$B22,资产负债表!$C:$C,G$3)=0,SUMIFS(资产负债表!$M:$M,资产负债表!$B:$B,$B22,资产负债表!$C:$C,G$3-1)=0),"",((SUMIFS(资产负债表!$I:$I,资产负债表!$B:$B,$B22,资产负债表!$C:$C,G$3)+SUMIFS(资产负债表!$I:$I,资产负债表!$B:$B,$B22,资产负债表!$C:$C,G$3-1))/2)/((SUMIFS(资产负债表!$M:$M,资产负债表!$B:$B,$B22,资产负债表!$C:$C,G$3)+SUMIFS(资产负债表!$M:$M,资产负债表!$B:$B,$B22,资产负债表!$C:$C,G$3-1))/2)) -> 1.8512948
A24: 因子乘积复核(=ROE) | B24: 苏泊尔 | C24: =IF(OR(C9="",C14="",C19=""),"",C9*C14*C19) -> 0.26227722 | D24: =IF(OR(D9="",D14="",D19=""),"",D9*D14*D19) -> 0.28210633 | E24: =IF(OR(E9="",E14="",E19=""),"",E9*E14*E19) -> 0.32579479 | F24: =IF(OR(F9="",F14="",F19=""),"",F9*F14*F19) -> 0.35152528 | G24: =IF(OR(G9="",G14="",G19=""),"",G9*G14*G19) -> 0.32995122
A25: 因子乘积复核(=ROE) | B25: 九阳股份 | C25: =IF(OR(C10="",C15="",C20=""),"",C10*C15*C20) | D25: =IF(OR(D10="",D15="",D20=""),"",D10*D15*D20) | E25: =IF(OR(E10="",E15="",E20=""),"",E10*E15*E20) -> 0.11467937 | F25: =IF(OR(F10="",F15="",F20=""),"",F10*F15*F20) -> 0.035172459 | G25: =IF(OR(G10="",G15="",G20=""),"",G10*G15*G20) -> 0.034005917
A26: 因子乘积复核(=ROE) | B26: 小熊电器 | C26: =IF(OR(C11="",C16="",C21=""),"",C11*C16*C21) | D26: =IF(OR(D11="",D16="",D21=""),"",D11*D16*D21) | E26: =IF(OR(E11="",E16="",E21=""),"",E11*E16*E21) -> 0.17451193 | F26: =IF(OR(F11="",F16="",F21=""),"",F11*F16*F21) -> 0.10353889 | G26: =IF(OR(G11="",G16="",G21=""),"",G11*G16*G21) -> 0.13353906
A27: 因子乘积复核(=ROE) | B27: 新宝股份 | C27: =IF(OR(C12="",C17="",C22=""),"",C12*C17*C22) | D27: =IF(OR(D12="",D17="",D22=""),"",D12*D17*D22) | E27: =IF(OR(E12="",E17="",E22=""),"",E12*E17*E22) -> 0.13417369 | F27: =IF(OR(F12="",F17="",F22=""),"",F12*F17*F22) -> 0.13289128 | G27: =IF(OR(G12="",G17="",G22=""),"",G12*G17*G22) -> 0.11837575
A29: 验证ROE | B29: 苏泊尔 | C29: =C24=C4 -> TRUE | D29: =D24=D4 -> TRUE | E29: =E24=E4 -> TRUE | F29: =F24=F4 -> TRUE | G29: =G24=G4 -> TRUE
A30: 验证ROE | B30: 九阳股份 | C30: =C25=C5 -> TRUE | D30: =D25=D5 -> TRUE | E30: =E25=E5 -> TRUE | F30: =F25=F5 -> TRUE | G30: =G25=G5 -> TRUE
A31: 验证ROE | B31: 小熊电器 | C31: =C26=C6 -> TRUE | D31: =D26=D6 -> TRUE | E31: =E26=E6 -> TRUE | F31: =F26=F6 -> TRUE | G31: =G26=G6 -> TRUE
A32: 验证ROE | B32: 新宝股份 | C32: =C27=C7 -> TRUE | D32: =D27=D7 -> TRUE | E32: =E27=E7 -> TRUE | F32: =F27=F7 -> TRUE | G32: =G27=G7 -> TRUE
